tracesmith/__init__.py
tracesmith/__main__.py
tracesmith/_tracesmith.cpython-313-darwin.so
tracesmith/cli.py
tracesmith/xctrace.py
tracesmith-0.8.3.dist-info/LICENSE
tracesmith-0.8.3.dist-info/METADATA
tracesmith-0.8.3.dist-info/WHEEL
tracesmith-0.8.3.dist-info/entry_points.txt
tracesmith-0.8.3.dist-info/top_level.txt
tracesmith-0.8.3.dist-info/RECORD
