Metadata-Version: 2.1
Name: tracesmith
Version: 0.8.3
Summary: Cross-platform GPU profiling and replay system
Home-page: https://github.com/chenxingqiang/TraceSmith
Author: Xingqiang Chen
Author-email: TraceSmith Authors <tracesmith@example.com>
License: Apache-2.0
Project-URL: Homepage, https://github.com/xingqiangchen/TraceSmith
Project-URL: Documentation, https://github.com/xingqiangchen/TraceSmith#readme
Project-URL: Repository, https://github.com/xingqiangchen/TraceSmith.git
Project-URL: Issues, https://github.com/xingqiangchen/TraceSmith/issues
Project-URL: Changelog, https://github.com/xingqiangchen/TraceSmith/blob/main/CHANGELOG.md
Keywords: gpu,profiling,cuda,metal,rocm,tracing,performance,debugging,replay
Classifier: Development Status :: 4 - Beta
Classifier: Intended Audience :: Developers
Classifier: Intended Audience :: Science/Research
Classifier: Operating System :: POSIX :: Linux
Classifier: Operating System :: MacOS :: MacOS X
Classifier: Operating System :: Microsoft :: Windows
Classifier: Programming Language :: Python :: 3
Classifier: Programming Language :: Python :: 3.9
Classifier: Programming Language :: Python :: 3.10
Classifier: Programming Language :: Python :: 3.11
Classifier: Programming Language :: Python :: 3.12
Classifier: Programming Language :: C++
Classifier: Topic :: Scientific/Engineering
Classifier: Topic :: Software Development :: Debuggers
Classifier: Topic :: System :: Monitoring
Requires-Python: >=3.8
License-File: LICENSE
Requires-Dist: numpy>=1.20.0
Provides-Extra: all
Requires-Dist: numpy; extra == "all"
Requires-Dist: matplotlib; extra == "all"
Requires-Dist: plotly; extra == "all"
Provides-Extra: cuda
Provides-Extra: cuda11
Requires-Dist: cupy-cuda11x>=12.0.0; extra == "cuda11"
Provides-Extra: cuda118
Requires-Dist: cupy-cuda118>=12.0.0; extra == "cuda118"
Provides-Extra: cuda12
Requires-Dist: cupy-cuda12x>=12.0.0; extra == "cuda12"
Provides-Extra: cuda120
Requires-Dist: cupy-cuda120>=12.0.0; extra == "cuda120"
Provides-Extra: dev
Requires-Dist: pytest>=7.0.0; extra == "dev"
Requires-Dist: ruff>=0.1.0; extra == "dev"
Requires-Dist: mypy>=1.0.0; extra == "dev"
Requires-Dist: build>=1.0.0; extra == "dev"
Requires-Dist: twine>=4.0.0; extra == "dev"
Provides-Extra: docs
Requires-Dist: sphinx>=7.0.0; extra == "docs"
Requires-Dist: sphinx-rtd-theme>=2.0.0; extra == "docs"
Requires-Dist: myst-parser>=2.0.0; extra == "docs"
Provides-Extra: rocm
Provides-Extra: torch
Requires-Dist: torch>=1.9; extra == "torch"
Provides-Extra: visualization
Requires-Dist: matplotlib; extra == "visualization"
Requires-Dist: plotly; extra == "visualization"
